python_dag_runner/__init__.py
python_dag_runner/dag.py
python_dag_runner/task.py
python_dag_runner/lib/__init__.py
python_dag_runner/lib/constants.py
python_dag_runner/lib/exceptions.py
python_dag_runner-0.0.5.dist-info/LICENSE
python_dag_runner-0.0.5.dist-info/METADATA
python_dag_runner-0.0.5.dist-info/WHEEL
python_dag_runner-0.0.5.dist-info/top_level.txt
python_dag_runner-0.0.5.dist-info/RECORD
