Metadata-Version: 2.1
Name: python-dag-runner
Version: 0.0.5
Summary: Run tasks as a DAG
Home-page: https://github.com/jatinlal1994/python-dag-runner
Author: Jatin Lal
Author-email: jatinlal1994@gmail.com
Keywords: python,dag,runner
Classifier: Development Status :: 3 - Alpha
Classifier: Intended Audience :: Developers
Classifier: Programming Language :: Python :: 3.8
Classifier: Programming Language :: Python :: 3.9
Classifier: Programming Language :: Python :: 3.10
Classifier: Programming Language :: Python :: 3.11
Classifier: Programming Language :: Python :: 3.12
Classifier: Topic :: Software Development :: Libraries :: Python Modules
License-File: LICENSE
Requires-Dist: networkx
